web3_etl_schemas/__init__.py
web3_etl_schemas/models/__init__.py
web3_etl_schemas/models/common.py
web3_etl_schemas/models/ethereum.py
web3_etl_schemas-0.1.2.dist-info/METADATA
web3_etl_schemas-0.1.2.dist-info/WHEEL
web3_etl_schemas-0.1.2.dist-info/RECORD
